{
  "project_info": {
    "project_number": "750693689760",
    "project_id": "xenon-tracer-385806",
    "storage_bucket": "xenon-tracer-385806.appspot.com"
  },
  "client": [
    {
      "client_info": {
        "mobilesdk_app_id": "1:750693689760:android:ad11c647db874365b89cc5",
        "android_client_info": {
          "package_name": "com.Fintech.flutter_application_4"
        }
      },
      "oauth_client": [
        {
          "client_id": "750693689760-n65r776bcdqd0kfbq8mmpfnah29tvf3l.apps.googleusercontent.com",
          "client_type": 3
        }
      ],
      "api_key": [
        {
          "current_key": "AIzaSyBrN7YBuxvLqO45s9TJoO0ofjvghI0jlwM"
        }
      ],
      "services": {
        "appinvite_service": {
          "other_platform_oauth_client": [
            {
              "client_id": "750693689760-n65r776bcdqd0kfbq8mmpfnah29tvf3l.apps.googleusercontent.com",
              "client_type": 3
            }
          ]
        }
      }
    }
  ],
  "configuration_version": "1"
}